{"file":"Footer.vue.mjs","mappings":";;;;;AAgDA,KAAK,eAAe,aAAa;AAEjC,MAAK,YAAU;AAAA,EACb,MAAM;AAAA,EACN,QAAQ;AAEgB,QAAI,IAAI;AACR,QAAI,CAAE,CAAA;AACP,QAAI,IAAI;AAG7B,UAAM,cAAc,SAAS,2BAAU,KAAK,GAAE,aAAa;AA4DpD,WAAA;AAAA,MACL;AAAA,IACF;AAAA,EAAA;AAEJ;;AA3HA,QAAA,UAAAA,eAAAC,WACU,EAAA,OAAM,SADhB,GAAA,MAAA,CAAA,4iDAAAC,eAqCwC,OAAW,WAAA;;;;;;;;;","names":["_ssrRenderAttrs","_mergeProps","_ssrInterpolate"],"sources":["../../../../components/Footer.vue"],"sourcesContent":["<template>\r\n  <footer class=\"footer\">\r\n    <div class=\"footer-line\"></div>\r\n    <div class=\"footer-container\">\r\n      <div class=\"footer-content\">\r\n        <div class=\"footer-column\">\r\n          <h3>Контактная информация</h3>\r\n          <ul>\r\n            <li>Адрес: г. Москва, ул. Примерная, д. 123</li>\r\n            <li>Телефон: +7 (999) 123-45-67</li>\r\n            <li>Email: <a href=\"mailto:info@webdev-site.ru\">info@webdev-site.ru</a></li>\r\n            <li>Режим работы: Пн-Пт: 9:00 - 18:00</li>\r\n          </ul>\r\n        </div>\r\n        <div class=\"footer-column\">\r\n          <h3>Мы в соцсетях</h3>\r\n          <ul>\r\n            <li><a href=\"#\">VK</a></li>\r\n            <li><a href=\"#\">Telegram</a></li>\r\n            <li><a href=\"#\">Instagram</a></li>\r\n            <li><a href=\"#\">YouTube</a></li>\r\n          </ul>\r\n        </div>\r\n        <div class=\"footer-column\">\r\n          <h3>Быстрые ссылки</h3>\r\n          <ul>\r\n            <li><a href=\"#\">Главная</a></li>\r\n            <li><a href=\"#\">Услуги</a></li>\r\n            <li><a href=\"#\">Портфолио</a></li>\r\n            <li><a href=\"#\">О нас</a></li>\r\n            <li><a href=\"#\">Блог</a></li>\r\n            <li><a href=\"#\">Контакты</a></li>\r\n          </ul>\r\n        </div>\r\n      </div>\r\n      <div class=\"footer-bottom\">\r\n        <p class=\"footer-legal\">Юридическая информация</p>\r\n        <p class=\"footer-copyright\">©{{ currentYear }} DevX. Все права защищены · <a href=\"#\">Политика конфиденциальности</a> · <a href=\"#\">Пользовательское соглашение</a></p>\r\n      </div>\r\n    </div>\r\n  </footer>\r\n</template>\r\n\r\n<script>\r\nimport { ref, onMounted, computed } from 'vue';\r\nimport gsap from 'gsap';\r\nimport { ScrollTrigger } from 'gsap/ScrollTrigger';\r\n\r\ngsap.registerPlugin(ScrollTrigger);\r\n\r\nexport default {\r\n  name: 'Footer',\r\n  setup() {\r\n    // Refs для элементов анимации\r\n    const footerElement = ref(null);\r\n    const footerColumns = ref([]);\r\n    const footerBottom = ref(null);\r\n    \r\n    // Получаем текущий год для копирайта\r\n    const currentYear = computed(() => new Date().getFullYear());\r\n    \r\n    // Функция анимации футера\r\n    const animateFooter = () => {\r\n      const columns = Array.from(document.querySelectorAll('.footer-column'));\r\n      const bottom = document.querySelector('.footer-bottom');\r\n      \r\n      if (columns.length && bottom) {\r\n        const timeline = gsap.timeline({\r\n          scrollTrigger: {\r\n            trigger: '.footer',\r\n            start: 'top 80%',\r\n            end: 'bottom 20%',\r\n            toggleActions: 'play none none none'\r\n          }\r\n        });\r\n        \r\n        timeline\r\n          .from('.footer-line', {\r\n            width: 0,\r\n            duration: 1,\r\n            ease: 'power2.out'\r\n          })\r\n          .from(columns, {\r\n            y: 30,\r\n            opacity: 0,\r\n            stagger: 0.2,\r\n            duration: 0.8,\r\n            ease: 'power2.out'\r\n          }, '-=0.5')\r\n          .from(bottom, {\r\n            y: 20,\r\n            opacity: 0,\r\n            duration: 0.6,\r\n            ease: 'power2.out'\r\n          }, '-=0.3');\r\n      }\r\n    };\r\n    \r\n    // Обработка изменения размера окна\r\n    const handleResize = () => {\r\n      // Очищаем все анимации ScrollTrigger\r\n      ScrollTrigger.getAll().forEach(trigger => trigger.kill());\r\n      \r\n      // Переинициализируем анимации\r\n      setTimeout(() => {\r\n        animateFooter();\r\n      }, 300);\r\n    };\r\n    \r\n    onMounted(() => {\r\n      // Небольшая задержка для уверенности, что DOM полностью загружен\r\n      setTimeout(() => {\r\n        animateFooter();\r\n      }, 500);\r\n      \r\n      // Добавляем обработчик изменения размера окна\r\n      window.addEventListener('resize', handleResize);\r\n    });\r\n    \r\n    return {\r\n      currentYear\r\n    };\r\n  }\r\n};\r\n</script>\r\n\r\n<style scoped>\r\n/* Footer */\r\n.footer {\r\n  color: var(--text-color);\r\n  padding: 120px 0 30px;\r\n  position: relative;\r\n  width: 100%;\r\n  overflow: hidden;\r\n}\r\n\r\n.footer-container {\r\n  margin: 0 auto;\r\n  width: 100%;\r\n  padding: 0 20px;\r\n  overflow: hidden;\r\n}\r\n\r\n.footer-line {\r\n  height: 2px;\r\n  background-image: var(--background-image-footer-line);\r\n  background-repeat: no-repeat;\r\n  background-size: cover;\r\n  margin-bottom: 40px;\r\n  width: 100vw;\r\n  position: relative;\r\n  left: 50%;\r\n  right: 50%;\r\n  margin-left: -50vw;\r\n  margin-right: -50vw;\r\n}\r\n\r\n.footer-content {\r\n  display: flex;\r\n  flex-wrap: wrap;\r\n  justify-content: space-between;\r\n  margin-bottom: 40px;\r\n  align-items: flex-start;\r\n}\r\n\r\n.footer-column {\r\n  flex: 1;\r\n  min-width: 250px;\r\n  margin-bottom: 30px;\r\n  display: flex;\r\n  flex-direction: column;\r\n  align-items: center;\r\n  justify-content: flex-start;\r\n}\r\n\r\n.footer-column h3 {\r\n  font-weight: 400;\r\n  font-size: 24px;\r\n  margin-bottom: 20px;\r\n  color: var(--text-hover-color);\r\n  text-align: center;\r\n}\r\n\r\n.footer-column ul {\r\n  list-style: none;\r\n  padding: 0;\r\n  width: 100%;\r\n  text-align: center;\r\n}\r\n\r\n.footer-column ul li {\r\n  color: var(--text-color);\r\n  font-weight: 400;\r\n  margin-bottom: 10px;\r\n  font-size: 18px;\r\n  display: flex;\r\n  align-items: center;\r\n  justify-content: center;\r\n}\r\n\r\n.footer-column ul li::before {\r\n  content: \"•\";\r\n  margin-right: 10px;\r\n  color: var(--text-color);\r\n}\r\n\r\n.footer-column a {\r\n  color: var(--text-color);\r\n  text-decoration: none;\r\n  transition: color 0.3s ease;\r\n}\r\n\r\n.footer-column a:hover {\r\n  color: var(--text-hover-color);\r\n}\r\n\r\n.footer-bottom {\r\n  position: relative;\r\n  padding-top: 20px;\r\n  text-align: center;\r\n  overflow: visible;\r\n}\r\n\r\n.footer-bottom::before {\r\n  content: \"\";\r\n  position: absolute;\r\n  top: 0;\r\n  left: 0;\r\n  width: 100vw;\r\n  height: 1px;\r\n  background-color: var(--text-color);\r\n  opacity: 0.2;\r\n  transform: translateX(calc((100% - 100vw) / 2));\r\n}\r\n\r\n.footer-legal {\r\n  font-weight: 700;\r\n  font-size: 18px;\r\n  margin-bottom: 10px;\r\n  color: var(--text-hover-color);\r\n}\r\n\r\n.footer-copyright {\r\n  font-size: 14px;\r\n  color: var(--text-color);\r\n  opacity: 0.7;\r\n}\r\n\r\n.footer-copyright a {\r\n  color: var(--text-color);\r\n  text-decoration: none;\r\n}\r\n\r\n.footer-copyright a:hover {\r\n  text-decoration: underline;\r\n}\r\n\r\n/* Адаптивность */\r\n@media (max-width: 992px) {\r\n  .footer-column h3 {\r\n    font-size: 22px;\r\n  }\r\n  \r\n  .footer-column ul li {\r\n    font-size: 16px;\r\n  }\r\n}\r\n\r\n@media (max-width: 768px) {\r\n  .footer-content {\r\n    flex-direction: column;\r\n    align-items: center;\r\n  }\r\n  \r\n  .footer-column {\r\n    width: 100%;\r\n    max-width: 500px;\r\n    margin-bottom: 30px;\r\n  }\r\n  \r\n  .footer-column:last-child {\r\n    margin-bottom: 0;\r\n  }\r\n}\r\n\r\n@media (max-width: 576px) {\r\n  .footer {\r\n    padding: 80px 0 20px;\r\n  }\r\n  \r\n  .footer-column h3 {\r\n    font-size: 20px;\r\n  }\r\n  \r\n  .footer-column ul li {\r\n    font-size: 14px;\r\n  }\r\n  \r\n  .footer-legal {\r\n    font-size: 16px;\r\n  }\r\n  \r\n  .footer-copyright {\r\n    font-size: 12px;\r\n  }\r\n}\r\n</style>\r\n"],"version":3}